{
  "asOf": "2014-10-30",
  "configHash": "a1f27d7d0c379a5624463feb7d72defc5c93b677ca716722c536942a2ac71b3c",
  "meta": {
    "noFutureLeakOk": true,
    "predDtBuy": null,
    "predDtSell": null,
    "requestedAsOf": "2014-10-30"
  },
  "mode": "LIVE",
  "policyVersion": "toredex.v8",
  "positions": [
    {
      "avgPrice": 15291.0,
      "holdingDays": 4,
      "openedAt": "2014-10-24",
      "pnlPct": 2.400104636714407,
      "side": "LONG",
      "stage": "PROBE",
      "ticker": "1001",
      "units": 2
    },
    {
      "avgPrice": 1270.0,
      "holdingDays": 4,
      "openedAt": "2014-10-24",
      "pnlPct": -2.9133858267716537,
      "side": "SHORT",
      "stage": "PROBE",
      "ticker": "1306",
      "units": 2
    },
    {
      "avgPrice": 1268.0,
      "holdingDays": 3,
      "openedAt": "2014-10-27",
      "pnlPct": 1.8927444794952681,
      "side": "LONG",
      "stage": "PROBE",
      "ticker": "1308",
      "units": 2
    }
  ],
  "rankings": {
    "buy": [
      {
        "changePct": 0.0067511091107824855,
        "close": 15658.0,
        "entryScore": 0.5584463983906737,
        "ev": 0.0067511091107824855,
        "ev20Net": null,
        "gate": {
          "ok": true,
          "reason": "ENTRY_OK"
        },
        "liquidity20d": 3559973080.1,
        "pDown": null,
        "pTurnDown": null,
        "regime": "RANGE",
        "revRisk": 0.6175373122670769,
        "sector": "",
        "shortable": true,
        "sourceAsOf": "2014-10-30",
        "ticker": "1001",
        "timeframeSignals": {
          "frameState": "MIXED",
          "monthlyBoxMonths": 13.0,
          "monthlyBoxPos": 0.6814292903875189,
          "monthlyBoxRangePct": 0.138912192393736,
          "monthlyBoxState": "box_mid",
          "monthlyBoxWild": false,
          "monthlyBreakoutDownProb": 0.5124262994934854,
          "monthlyBreakoutUpProb": 0.6394268027647486,
          "monthlyRangePos": 0.6814292903875189,
          "monthlyRangeProb": 0.6968217844267841,
          "monthlyRangeWidth": 0.12196918543981339,
          "monthlyRegimeAligned": null,
          "weeklyBreakoutDownProb": 0.6175373122670769,
          "weeklyBreakoutUpProb": 0.564518866207826,
          "weeklyRangeProb": 0.7886511139486461,
          "weeklyRegimeAligned": null
        },
        "upProb": 0.564518866207826
      },
      {
        "changePct": 0.006158583525789068,
        "close": 1307.0,
        "entryScore": 0.556076795420323,
        "ev": 0.006158583525789068,
        "ev20Net": null,
        "gate": {
          "ok": true,
          "reason": "ENTRY_OK"
        },
        "liquidity20d": 5585610.6,
        "pDown": null,
        "pTurnDown": null,
        "regime": "RANGE",
        "revRisk": 0.6118751407238237,
        "sector": "",
        "shortable": true,
        "sourceAsOf": "2014-10-30",
        "ticker": "1306",
        "timeframeSignals": {
          "frameState": "MIXED",
          "monthlyBoxMonths": 13.0,
          "monthlyBoxPos": 0.689873417721519,
          "monthlyBoxRangePct": 0.1318864774624374,
          "monthlyBoxState": "box_mid",
          "monthlyBoxWild": false,
          "monthlyBreakoutDownProb": 0.5138529008946003,
          "monthlyBreakoutUpProb": 0.6561109654107294,
          "monthlyRangePos": 0.7032258064516129,
          "monthlyRangeProb": 0.6922660383006567,
          "monthlyRangeWidth": 0.11456023651145603,
          "monthlyRegimeAligned": null,
          "weeklyBreakoutDownProb": 0.6118751407238237,
          "weeklyBreakoutUpProb": 0.5561426566473905,
          "weeklyRangeProb": 0.7776416689156479,
          "weeklyRegimeAligned": null
        },
        "upProb": 0.5561426566473905
      },
      {
        "changePct": 0.006230529595015576,
        "close": 1292.0,
        "entryScore": 0.5545574375720992,
        "ev": 0.006230529595015576,
        "ev20Net": null,
        "gate": {
          "ok": true,
          "reason": "ENTRY_OK"
        },
        "liquidity20d": 1096110.95,
        "pDown": null,
        "pTurnDown": null,
        "regime": "RANGE",
        "revRisk": 0.614737626952553,
        "sector": "",
        "shortable": true,
        "sourceAsOf": "2014-10-30",
        "ticker": "1308",
        "timeframeSignals": {
          "frameState": "MIXED",
          "monthlyBoxMonths": 13.0,
          "monthlyBoxPos": 0.6942675159235668,
          "monthlyBoxRangePct": 0.1327134404057481,
          "monthlyBoxState": "box_mid",
          "monthlyBoxWild": false,
          "monthlyBreakoutDownProb": 0.5122831916250113,
          "monthlyBreakoutUpProb": 0.6545412561411404,
          "monthlyRangePos": 0.7032258064516129,
          "monthlyRangeProb": 0.6904109273456879,
          "monthlyRangeWidth": 0.11584454409566518,
          "monthlyRegimeAligned": null,
          "weeklyBreakoutDownProb": 0.614737626952553,
          "weeklyBreakoutUpProb": 0.553769885017069,
          "weeklyRangeProb": 0.7726957878647472,
          "weeklyRegimeAligned": null
        },
        "upProb": 0.553769885017069
      }
    ],
    "sell": [
      {
        "changePct": 0.0067511091107824855,
        "close": 15658.0,
        "entryScore": 0.5395899677212045,
        "ev": 0.0067511091107824855,
        "ev20Net": null,
        "gate": {
          "ok": true,
          "reason": "ENTRY_OK"
        },
        "liquidity20d": 3559973080.1,
        "pDown": null,
        "pTurnDown": null,
        "regime": "RANGE",
        "revRisk": 0.6175373122670769,
        "sector": "",
        "shortable": true,
        "sourceAsOf": "2014-10-30",
        "ticker": "1001",
        "timeframeSignals": {
          "frameState": "MIXED",
          "monthlyBoxMonths": 13.0,
          "monthlyBoxPos": 0.6814292903875189,
          "monthlyBoxRangePct": 0.138912192393736,
          "monthlyBoxState": "box_mid",
          "monthlyBoxWild": false,
          "monthlyBreakoutDownProb": 0.5124262994934854,
          "monthlyBreakoutUpProb": 0.6394268027647486,
          "monthlyRangePos": 0.6814292903875189,
          "monthlyRangeProb": 0.6968217844267841,
          "monthlyRangeWidth": 0.12196918543981339,
          "monthlyRegimeAligned": null,
          "weeklyBreakoutDownProb": 0.6175373122670769,
          "weeklyBreakoutUpProb": 0.564518866207826,
          "weeklyRangeProb": 0.7886511139486461,
          "weeklyRegimeAligned": null
        },
        "upProb": 0.6175373122670769
      },
      {
        "changePct": 0.006230529595015576,
        "close": 1292.0,
        "entryScore": 0.5388859443984052,
        "ev": 0.006230529595015576,
        "ev20Net": null,
        "gate": {
          "ok": true,
          "reason": "ENTRY_OK"
        },
        "liquidity20d": 1096110.95,
        "pDown": null,
        "pTurnDown": null,
        "regime": "RANGE",
        "revRisk": 0.614737626952553,
        "sector": "",
        "shortable": true,
        "sourceAsOf": "2014-10-30",
        "ticker": "1308",
        "timeframeSignals": {
          "frameState": "MIXED",
          "monthlyBoxMonths": 13.0,
          "monthlyBoxPos": 0.6942675159235668,
          "monthlyBoxRangePct": 0.1327134404057481,
          "monthlyBoxState": "box_mid",
          "monthlyBoxWild": false,
          "monthlyBreakoutDownProb": 0.5122831916250113,
          "monthlyBreakoutUpProb": 0.6545412561411404,
          "monthlyRangePos": 0.7032258064516129,
          "monthlyRangeProb": 0.6904109273456879,
          "monthlyRangeWidth": 0.11584454409566518,
          "monthlyRegimeAligned": null,
          "weeklyBreakoutDownProb": 0.614737626952553,
          "weeklyBreakoutUpProb": 0.553769885017069,
          "weeklyRangeProb": 0.7726957878647472,
          "weeklyRegimeAligned": null
        },
        "upProb": 0.614737626952553
      },
      {
        "changePct": 0.006158583525789068,
        "close": 1307.0,
        "entryScore": 0.5377202300829086,
        "ev": 0.006158583525789068,
        "ev20Net": null,
        "gate": {
          "ok": true,
          "reason": "ENTRY_OK"
        },
        "liquidity20d": 5585610.6,
        "pDown": null,
        "pTurnDown": null,
        "regime": "RANGE",
        "revRisk": 0.6118751407238237,
        "sector": "",
        "shortable": true,
        "sourceAsOf": "2014-10-30",
        "ticker": "1306",
        "timeframeSignals": {
          "frameState": "MIXED",
          "monthlyBoxMonths": 13.0,
          "monthlyBoxPos": 0.689873417721519,
          "monthlyBoxRangePct": 0.1318864774624374,
          "monthlyBoxState": "box_mid",
          "monthlyBoxWild": false,
          "monthlyBreakoutDownProb": 0.5138529008946003,
          "monthlyBreakoutUpProb": 0.6561109654107294,
          "monthlyRangePos": 0.7032258064516129,
          "monthlyRangeProb": 0.6922660383006567,
          "monthlyRangeWidth": 0.11456023651145603,
          "monthlyRegimeAligned": null,
          "weeklyBreakoutDownProb": 0.6118751407238237,
          "weeklyBreakoutUpProb": 0.5561426566473905,
          "weeklyRangeProb": 0.7776416689156479,
          "weeklyRegimeAligned": null
        },
        "upProb": 0.6118751407238237
      }
    ]
  },
  "seasonId": "toredex_multiframe_20260318",
  "universe": [
    "1001",
    "1306",
    "1308"
  ]
}