{
  "asOf": "2005-06-01",
  "configHash": "a1f27d7d0c379a5624463feb7d72defc5c93b677ca716722c536942a2ac71b3c",
  "meta": {
    "noFutureLeakOk": true,
    "predDtBuy": null,
    "predDtSell": null,
    "requestedAsOf": "2005-06-01"
  },
  "mode": "LIVE",
  "policyVersion": "toredex.v8",
  "positions": [],
  "rankings": {
    "buy": [
      {
        "changePct": 0.004700248315005321,
        "close": 11329.0,
        "entryScore": 0.5293290004429207,
        "ev": 0.004700248315005321,
        "ev20Net": null,
        "gate": {
          "ok": false,
          "reason": "SETUP_reject"
        },
        "liquidity20d": 1447577671.2,
        "pDown": null,
        "pTurnDown": null,
        "regime": "RANGE",
        "revRisk": 0.7358211822766212,
        "sector": "",
        "shortable": true,
        "sourceAsOf": "2005-06-01",
        "ticker": "1001",
        "timeframeSignals": {
          "frameState": "BEARISH",
          "monthlyBoxMonths": 14.0,
          "monthlyBoxPos": 0.49750415973377704,
          "monthlyBoxRangePct": 0.11201192805889479,
          "monthlyBoxState": "box_mid",
          "monthlyBoxWild": false,
          "monthlyBreakoutDownProb": 0.6082924318566321,
          "monthlyBreakoutUpProb": 0.6176300583515724,
          "monthlyRangePos": 0.5133394664213431,
          "monthlyRangeProb": 0.858252935900817,
          "monthlyRangeWidth": 0.09166807218755271,
          "monthlyRegimeAligned": null,
          "weeklyBreakoutDownProb": 0.7358211822766212,
          "weeklyBreakoutUpProb": 0.5265862095990255,
          "weeklyRangeProb": 0.6799148497943773,
          "weeklyRegimeAligned": null
        },
        "upProb": 0.5265862095990255
      },
      {
        "changePct": 0.0034453057708871662,
        "close": 1165.0,
        "entryScore": 0.5232002859634528,
        "ev": 0.0034453057708871662,
        "ev20Net": null,
        "gate": {
          "ok": false,
          "reason": "SETUP_reject"
        },
        "liquidity20d": 5652781.8,
        "pDown": null,
        "pTurnDown": null,
        "regime": "RANGE",
        "revRisk": 0.7847885334062529,
        "sector": "",
        "shortable": true,
        "sourceAsOf": "2005-06-01",
        "ticker": "1306",
        "timeframeSignals": {
          "frameState": "BEARISH",
          "monthlyBoxMonths": 14.0,
          "monthlyBoxPos": 0.6299212598425197,
          "monthlyBoxRangePct": 0.11705069124423963,
          "monthlyBoxState": "box_mid",
          "monthlyBoxWild": false,
          "monthlyBreakoutDownProb": 0.5540757749712973,
          "monthlyBreakoutUpProb": 0.6587766296721521,
          "monthlyRangePos": 0.6495726495726496,
          "monthlyRangeProb": 0.755166475315729,
          "monthlyRangeWidth": 0.09701492537313433,
          "monthlyRegimeAligned": null,
          "weeklyBreakoutDownProb": 0.7847885334062529,
          "weeklyBreakoutUpProb": 0.5047885334062528,
          "weeklyRangeProb": 0.6252046303892078,
          "weeklyRegimeAligned": null
        },
        "upProb": 0.5047885334062528
      },
      {
        "changePct": 0.0034602076124567475,
        "close": 1160.0,
        "entryScore": 0.5186008560407309,
        "ev": 0.0034602076124567475,
        "ev20Net": null,
        "gate": {
          "ok": false,
          "reason": "SETUP_reject"
        },
        "liquidity20d": 129051.65,
        "pDown": null,
        "pTurnDown": null,
        "regime": "RANGE",
        "revRisk": 0.7951418554881045,
        "sector": "",
        "shortable": true,
        "sourceAsOf": "2005-06-01",
        "ticker": "1308",
        "timeframeSignals": {
          "frameState": "BEARISH",
          "monthlyBoxMonths": 14.0,
          "monthlyBoxPos": 0.6124031007751938,
          "monthlyBoxRangePct": 0.11933395004625347,
          "monthlyBoxState": "box_mid",
          "monthlyBoxWild": false,
          "monthlyBreakoutDownProb": 0.5503416794965291,
          "monthlyBreakoutUpProb": 0.6499351754314885,
          "monthlyRangePos": 0.6422764227642277,
          "monthlyRangeProb": 0.7528428274315965,
          "monthlyRangeWidth": 0.10215946843853821,
          "monthlyRegimeAligned": null,
          "weeklyBreakoutDownProb": 0.7951418554881045,
          "weeklyBreakoutUpProb": 0.49968731003355904,
          "weeklyRangeProb": 0.6128535978082557,
          "weeklyRegimeAligned": null
        },
        "upProb": 0.49968731003355904
      }
    ],
    "sell": [
      {
        "changePct": 0.0034602076124567475,
        "close": 1160.0,
        "entryScore": 0.65227313335129,
        "ev": 0.0034602076124567475,
        "ev20Net": null,
        "gate": {
          "ok": true,
          "reason": "ENTRY_OK"
        },
        "liquidity20d": 129051.65,
        "pDown": null,
        "pTurnDown": null,
        "regime": "RANGE",
        "revRisk": 0.7951418554881045,
        "sector": "",
        "shortable": true,
        "sourceAsOf": "2005-06-01",
        "ticker": "1308",
        "timeframeSignals": {
          "frameState": "BEARISH",
          "monthlyBoxMonths": 14.0,
          "monthlyBoxPos": 0.6124031007751938,
          "monthlyBoxRangePct": 0.11933395004625347,
          "monthlyBoxState": "box_mid",
          "monthlyBoxWild": false,
          "monthlyBreakoutDownProb": 0.5503416794965291,
          "monthlyBreakoutUpProb": 0.6499351754314885,
          "monthlyRangePos": 0.6422764227642277,
          "monthlyRangeProb": 0.7528428274315965,
          "monthlyRangeWidth": 0.10215946843853821,
          "monthlyRegimeAligned": null,
          "weeklyBreakoutDownProb": 0.7951418554881045,
          "weeklyBreakoutUpProb": 0.49968731003355904,
          "weeklyRangeProb": 0.6128535978082557,
          "weeklyRegimeAligned": null
        },
        "upProb": 0.7951418554881045
      },
      {
        "changePct": 0.0034453057708871662,
        "close": 1165.0,
        "entryScore": 0.647247638094526,
        "ev": 0.0034453057708871662,
        "ev20Net": null,
        "gate": {
          "ok": true,
          "reason": "ENTRY_OK"
        },
        "liquidity20d": 5652781.8,
        "pDown": null,
        "pTurnDown": null,
        "regime": "RANGE",
        "revRisk": 0.7847885334062529,
        "sector": "",
        "shortable": true,
        "sourceAsOf": "2005-06-01",
        "ticker": "1306",
        "timeframeSignals": {
          "frameState": "BEARISH",
          "monthlyBoxMonths": 14.0,
          "monthlyBoxPos": 0.6299212598425197,
          "monthlyBoxRangePct": 0.11705069124423963,
          "monthlyBoxState": "box_mid",
          "monthlyBoxWild": false,
          "monthlyBreakoutDownProb": 0.5540757749712973,
          "monthlyBreakoutUpProb": 0.6587766296721521,
          "monthlyRangePos": 0.6495726495726496,
          "monthlyRangeProb": 0.755166475315729,
          "monthlyRangeWidth": 0.09701492537313433,
          "monthlyRegimeAligned": null,
          "weeklyBreakoutDownProb": 0.7847885334062529,
          "weeklyBreakoutUpProb": 0.5047885334062528,
          "weeklyRangeProb": 0.6252046303892078,
          "weeklyRegimeAligned": null
        },
        "upProb": 0.7847885334062529
      },
      {
        "changePct": 0.004700248315005321,
        "close": 11329.0,
        "entryScore": 0.6285179227633679,
        "ev": 0.004700248315005321,
        "ev20Net": null,
        "gate": {
          "ok": true,
          "reason": "ENTRY_OK"
        },
        "liquidity20d": 1447577671.2,
        "pDown": null,
        "pTurnDown": null,
        "regime": "RANGE",
        "revRisk": 0.7358211822766212,
        "sector": "",
        "shortable": true,
        "sourceAsOf": "2005-06-01",
        "ticker": "1001",
        "timeframeSignals": {
          "frameState": "BEARISH",
          "monthlyBoxMonths": 14.0,
          "monthlyBoxPos": 0.49750415973377704,
          "monthlyBoxRangePct": 0.11201192805889479,
          "monthlyBoxState": "box_mid",
          "monthlyBoxWild": false,
          "monthlyBreakoutDownProb": 0.6082924318566321,
          "monthlyBreakoutUpProb": 0.6176300583515724,
          "monthlyRangePos": 0.5133394664213431,
          "monthlyRangeProb": 0.858252935900817,
          "monthlyRangeWidth": 0.09166807218755271,
          "monthlyRegimeAligned": null,
          "weeklyBreakoutDownProb": 0.7358211822766212,
          "weeklyBreakoutUpProb": 0.5265862095990255,
          "weeklyRangeProb": 0.6799148497943773,
          "weeklyRegimeAligned": null
        },
        "upProb": 0.7358211822766212
      }
    ]
  },
  "seasonId": "toredex_multiframe_20260318",
  "universe": [
    "1001",
    "1306",
    "1308"
  ]
}