{
  "asOf": "2006-06-19",
  "configHash": "a1f27d7d0c379a5624463feb7d72defc5c93b677ca716722c536942a2ac71b3c",
  "meta": {
    "noFutureLeakOk": true,
    "predDtBuy": null,
    "predDtSell": null,
    "requestedAsOf": "2006-06-19"
  },
  "mode": "LIVE",
  "policyVersion": "toredex.v8",
  "positions": [
    {
      "avgPrice": 14879.0,
      "holdingDays": 1,
      "openedAt": "2006-06-16",
      "pnlPct": 0.12769675381410042,
      "side": "SHORT",
      "stage": "PROBE",
      "ticker": "1001",
      "units": 2
    }
  ],
  "rankings": {
    "buy": [
      {
        "changePct": -0.003213367609254499,
        "close": 1551.0,
        "entryScore": 0.39963407488018615,
        "ev": -0.003213367609254499,
        "ev20Net": null,
        "gate": {
          "ok": false,
          "reason": "SETUP_reject"
        },
        "liquidity20d": 7359181.4,
        "pDown": null,
        "pTurnDown": null,
        "regime": "RANGE",
        "revRisk": 0.6707274017616994,
        "sector": "",
        "shortable": true,
        "sourceAsOf": "2006-06-19",
        "ticker": "1306",
        "timeframeSignals": {
          "frameState": "BEARISH",
          "monthlyBoxMonths": 8.0,
          "monthlyBoxPos": 0.26353790613718414,
          "monthlyBoxRangePct": 0.18741542625169147,
          "monthlyBoxState": "box_mid",
          "monthlyBoxWild": false,
          "monthlyBreakoutDownProb": 0.2862416483383009,
          "monthlyBreakoutUpProb": 0.38858821873541277,
          "monthlyRangePos": 0.6462093862815884,
          "monthlyRangeProb": 0.4395983510555371,
          "monthlyRangeWidth": 0.31711505437893533,
          "monthlyRegimeAligned": null,
          "weeklyBreakoutDownProb": 0.6707274017616994,
          "weeklyBreakoutUpProb": 0.4010141401129539,
          "weeklyRangeProb": 0.5067703767317314,
          "weeklyRegimeAligned": null
        },
        "upProb": 0.4010141401129539
      },
      {
        "changePct": -0.0038634900193174502,
        "close": 1547.0,
        "entryScore": 0.39823951553004666,
        "ev": -0.0038634900193174502,
        "ev20Net": null,
        "gate": {
          "ok": false,
          "reason": "SETUP_reject"
        },
        "liquidity20d": 1455321.55,
        "pDown": null,
        "pTurnDown": null,
        "regime": "RANGE",
        "revRisk": 0.6629013702177281,
        "sector": "",
        "shortable": true,
        "sourceAsOf": "2006-06-19",
        "ticker": "1308",
        "timeframeSignals": {
          "frameState": "BEARISH",
          "monthlyBoxMonths": 8.0,
          "monthlyBoxPos": 0.26523297491039427,
          "monthlyBoxRangePct": 0.1894093686354379,
          "monthlyBoxState": "box_mid",
          "monthlyBoxWild": false,
          "monthlyBreakoutDownProb": 0.2842859853778457,
          "monthlyBreakoutUpProb": 0.3854529512665351,
          "monthlyRangePos": 0.644524236983842,
          "monthlyRangeProb": 0.4377696784920811,
          "monthlyRangeWidth": 0.31919770773638967,
          "monthlyRegimeAligned": null,
          "weeklyBreakoutDownProb": 0.6629013702177281,
          "weeklyBreakoutUpProb": 0.4016337645839253,
          "weeklyRangeProb": 0.5109577012944468,
          "weeklyRegimeAligned": null
        },
        "upProb": 0.4016337645839253
      },
      {
        "changePct": -0.0012769675381410041,
        "close": 14860.0,
        "entryScore": 0.3814631386100762,
        "ev": -0.0012769675381410041,
        "ev20Net": null,
        "gate": {
          "ok": false,
          "reason": "SETUP_reject"
        },
        "liquidity20d": 2938813727.05,
        "pDown": null,
        "pTurnDown": null,
        "regime": "RANGE",
        "revRisk": 0.6881907595597183,
        "sector": "",
        "shortable": true,
        "sourceAsOf": "2006-06-19",
        "ticker": "1001",
        "timeframeSignals": {
          "frameState": "BEARISH",
          "monthlyBoxMonths": 7.0,
          "monthlyBoxPos": 0.0,
          "monthlyBoxRangePct": 0.152557200538358,
          "monthlyBoxState": "box_lower",
          "monthlyBoxWild": false,
          "monthlyBreakoutDownProb": 0.29830928544795243,
          "monthlyBreakoutUpProb": 0.3671586005164456,
          "monthlyRangePos": 0.5983561643835617,
          "monthlyRangeProb": 0.46756352663774203,
          "monthlyRangeWidth": 0.3209449557418372,
          "monthlyRegimeAligned": null,
          "weeklyBreakoutDownProb": 0.6881907595597183,
          "weeklyBreakoutUpProb": 0.370291719389082,
          "weeklyRangeProb": 0.45074969739001836,
          "weeklyRegimeAligned": null
        },
        "upProb": 0.370291719389082
      }
    ],
    "sell": [
      {
        "changePct": -0.0012769675381410041,
        "close": 14860.0,
        "entryScore": 0.5500949125084174,
        "ev": -0.0012769675381410041,
        "ev20Net": null,
        "gate": {
          "ok": true,
          "reason": "ENTRY_OK"
        },
        "liquidity20d": 2938813727.05,
        "pDown": null,
        "pTurnDown": null,
        "regime": "RANGE",
        "revRisk": 0.6881907595597183,
        "sector": "",
        "shortable": true,
        "sourceAsOf": "2006-06-19",
        "ticker": "1001",
        "timeframeSignals": {
          "frameState": "BEARISH",
          "monthlyBoxMonths": 7.0,
          "monthlyBoxPos": 0.0,
          "monthlyBoxRangePct": 0.152557200538358,
          "monthlyBoxState": "box_lower",
          "monthlyBoxWild": false,
          "monthlyBreakoutDownProb": 0.29830928544795243,
          "monthlyBreakoutUpProb": 0.3671586005164456,
          "monthlyRangePos": 0.5983561643835617,
          "monthlyRangeProb": 0.46756352663774203,
          "monthlyRangeWidth": 0.3209449557418372,
          "monthlyRegimeAligned": null,
          "weeklyBreakoutDownProb": 0.6881907595597183,
          "weeklyBreakoutUpProb": 0.370291719389082,
          "weeklyRangeProb": 0.45074969739001836,
          "weeklyRegimeAligned": null
        },
        "upProb": 0.6881907595597183
      },
      {
        "changePct": -0.003213367609254499,
        "close": 1551.0,
        "entryScore": 0.5412214476986481,
        "ev": -0.003213367609254499,
        "ev20Net": null,
        "gate": {
          "ok": true,
          "reason": "ENTRY_OK"
        },
        "liquidity20d": 7359181.4,
        "pDown": null,
        "pTurnDown": null,
        "regime": "RANGE",
        "revRisk": 0.6707274017616994,
        "sector": "",
        "shortable": true,
        "sourceAsOf": "2006-06-19",
        "ticker": "1306",
        "timeframeSignals": {
          "frameState": "BEARISH",
          "monthlyBoxMonths": 8.0,
          "monthlyBoxPos": 0.26353790613718414,
          "monthlyBoxRangePct": 0.18741542625169147,
          "monthlyBoxState": "box_mid",
          "monthlyBoxWild": false,
          "monthlyBreakoutDownProb": 0.2862416483383009,
          "monthlyBreakoutUpProb": 0.38858821873541277,
          "monthlyRangePos": 0.6462093862815884,
          "monthlyRangeProb": 0.4395983510555371,
          "monthlyRangeWidth": 0.31711505437893533,
          "monthlyRegimeAligned": null,
          "weeklyBreakoutDownProb": 0.6707274017616994,
          "weeklyBreakoutUpProb": 0.4010141401129539,
          "weeklyRangeProb": 0.5067703767317314,
          "weeklyRegimeAligned": null
        },
        "upProb": 0.6707274017616994
      },
      {
        "changePct": -0.0038634900193174502,
        "close": 1547.0,
        "entryScore": 0.5375622330020411,
        "ev": -0.0038634900193174502,
        "ev20Net": null,
        "gate": {
          "ok": true,
          "reason": "ENTRY_OK"
        },
        "liquidity20d": 1455321.55,
        "pDown": null,
        "pTurnDown": null,
        "regime": "RANGE",
        "revRisk": 0.6629013702177281,
        "sector": "",
        "shortable": true,
        "sourceAsOf": "2006-06-19",
        "ticker": "1308",
        "timeframeSignals": {
          "frameState": "BEARISH",
          "monthlyBoxMonths": 8.0,
          "monthlyBoxPos": 0.26523297491039427,
          "monthlyBoxRangePct": 0.1894093686354379,
          "monthlyBoxState": "box_mid",
          "monthlyBoxWild": false,
          "monthlyBreakoutDownProb": 0.2842859853778457,
          "monthlyBreakoutUpProb": 0.3854529512665351,
          "monthlyRangePos": 0.644524236983842,
          "monthlyRangeProb": 0.4377696784920811,
          "monthlyRangeWidth": 0.31919770773638967,
          "monthlyRegimeAligned": null,
          "weeklyBreakoutDownProb": 0.6629013702177281,
          "weeklyBreakoutUpProb": 0.4016337645839253,
          "weeklyRangeProb": 0.5109577012944468,
          "weeklyRegimeAligned": null
        },
        "upProb": 0.6629013702177281
      }
    ]
  },
  "seasonId": "toredex_multiframe_20260318",
  "universe": [
    "1001",
    "1306",
    "1308"
  ]
}